cheek/__init__.py
cheek/cli.py
cheek/command_base.py
cheek/commands.py
cheek/version.py
cheek/extract/__init__.py
cheek/extract/__main__.py
cheek/extract/arg.py
cheek/extract/command.py
cheek-0.0.1.dist-info/LICENSE.rst
cheek-0.0.1.dist-info/METADATA
cheek-0.0.1.dist-info/WHEEL
cheek-0.0.1.dist-info/entry_points.txt
cheek-0.0.1.dist-info/top_level.txt
cheek-0.0.1.dist-info/zip-safe
cheek-0.0.1.dist-info/RECORD
