Metadata-Version: 2.1
Name: cheek
Version: 0.0.1
Summary: Python package for the Audacity scripting interface
Home-page: https://github.com/abingham/cheek
Author: Austin Bingham
Author-email: austin.bingham@gmail.com
License: MIT
Classifier: Development Status :: 4 - Beta
Classifier: Environment :: Console
Classifier: Intended Audience :: Information Technology
Classifier: License :: OSI Approved :: MIT License
Classifier: Programming Language :: Python :: 3.11
License-File: LICENSE.rst
Requires-Dist: click
Requires-Dist: pyaudacity
Requires-Dist: pydantic
Requires-Dist: typing-extensions
Provides-Extra: dev
Requires-Dist: bumpversion ; extra == 'dev'
Requires-Dist: build ; extra == 'dev'
Requires-Dist: twine ; extra == 'dev'
Requires-Dist: check-wheel-contents ; extra == 'dev'
Requires-Dist: flake8 ; extra == 'dev'
Requires-Dist: black ; extra == 'dev'
Provides-Extra: test
Requires-Dist: pytest ; extra == 'test'
